ra_mcp/__init__.py
ra_mcp/cli/__init__.py
ra_mcp/cli/cli.py
ra_mcp/cli/commands.py
ra_mcp/clients/__init__.py
ra_mcp/clients/alto_client.py
ra_mcp/clients/iiif_client.py
ra_mcp/clients/oai_pmh_client.py
ra_mcp/clients/search_client.py
ra_mcp/config.py
ra_mcp/formatters/__init__.py
ra_mcp/formatters/base_formatter.py
ra_mcp/formatters/plain_formatter.py
ra_mcp/formatters/rich_formatter.py
ra_mcp/formatters/utils.py
ra_mcp/models.py
ra_mcp/search_tools.py
ra_mcp/server.py
ra_mcp/services/__init__.py
ra_mcp/services/analysis.py
ra_mcp/services/display_service.py
ra_mcp/services/page_context_service.py
ra_mcp/services/search_enrichment_service.py
ra_mcp/services/search_operations.py
ra_mcp/utils/__init__.py
ra_mcp/utils/http_client.py
ra_mcp/utils/page_utils.py
ra_mcp/utils/url_generator.py
ra_mcp-0.1.0.dist-info/WHEEL
ra_mcp-0.1.0.dist-info/entry_points.txt
ra_mcp-0.1.0.dist-info/METADATA
ra_mcp-0.1.0.dist-info/RECORD
