Metadata-Version: 2.4
Name: ra-mcp
Version: 0.1.0
Summary: Riksarkivet first MCPs to expose APIs in dataplattformen and htrflow
Keywords: mcp,mcp server,model context protocol,ra-mcp,search,browse,iiif,llm,agent
License-Expression: Apache-2.0
Classifier: Intended Audience :: Developers
Classifier: Programming Language :: Python :: 3.12
Classifier: Typing :: Typed
Requires-Dist: asyncio>=4.0.0
Requires-Dist: fastmcp>=2.12.3
Requires-Dist: lxml>=6.0.2
Requires-Dist: pydantic>=2.11.9
Requires-Dist: rich>=14.1.0
Requires-Dist: starlette>=0.48.0
Requires-Dist: typer>=0.19.2
Requires-Dist: types-lxml>=2025.8.25
Requires-Python: >=3.12
